hybrid_recommender/__init__.py
hybrid_recommender/hybrid_recommender.py
hybrid_recommender-0.4.dist-info/METADATA
hybrid_recommender-0.4.dist-info/WHEEL
hybrid_recommender-0.4.dist-info/top_level.txt
hybrid_recommender-0.4.dist-info/RECORD
