Metadata-Version: 2.1
Name: hybrid-recommender
Version: 0.4
Summary: This package will create recommendations based on content as well as user ratings and finally providing top recommendations based on both data points
Home-page: https://github.com/devsahu99/hybrid_recommender
Author: Devendra Kumar Sahu
Author-email: devsahu99@gmail.com
License: UNKNOWN
Platform: UNKNOWN
Classifier: Programming Language :: Python :: 3
Classifier: License :: OSI Approved :: MIT License
Classifier: Operating System :: OS Independent
